tensorcraft/__init__.py
tensorcraft/arglib.py
tensorcraft/asynclib.py
tensorcraft/callbacks.py
tensorcraft/client.py
tensorcraft/errors.py
tensorcraft/handlers.py
tensorcraft/logging.py
tensorcraft/model.py
tensorcraft/server.py
tensorcraft/signal.py
tensorcraft/tlslib.py
tensorcraft/shell/__init__.py
tensorcraft/shell/commands.py
tensorcraft/shell/main.py
tensorcraft/shell/termlib.py
tensorcraft/storage/__init__.py
tensorcraft/storage/base.py
tensorcraft/storage/local.py
tensorcraft/storage/metadata.py
tensorcraft-0.0.1b5.dist-info/LICENSE.txt
tensorcraft-0.0.1b5.dist-info/METADATA
tensorcraft-0.0.1b5.dist-info/WHEEL
tensorcraft-0.0.1b5.dist-info/entry_points.txt
tensorcraft-0.0.1b5.dist-info/top_level.txt
tensorcraft-0.0.1b5.dist-info/RECORD
