Metadata-Version: 2.1
Name: tensorcraft
Version: 0.0.1b5
Summary: TensorCraft is a server for Keras models
Home-page: https://github.com/netrack/tensorcraft
Author: Yasha Bubnov
Author-email: girokompass@gmail.com
License: UNKNOWN
Platform: UNKNOWN
Classifier: Intended Audience :: Developers
Classifier: License :: OSI Approved :: MIT License
Requires-Dist: aiojobs (>=0.2.2)
Requires-Dist: aiofiles (>=0.4.0)
Requires-Dist: aiorwlock (>=0.6.0)
Requires-Dist: aiohttp (>=3.5.4)
Requires-Dist: flagparse (>=0.0.2)
Requires-Dist: humanize (>=0.5.1)
Requires-Dist: numpy (>=1.16.3)
Requires-Dist: pid (>=2.2.3)
Requires-Dist: pyyaml (>=5.1.1)
Requires-Dist: semver (>=2.8.1)
Requires-Dist: tensorflow (>=2.0.0a0)
Requires-Dist: tinydb (>=3.13.0)
